__init__.py
anum/RaizesFuncoes/__init__.py
anum/RaizesFuncoes/metodos_iterativos.py
anum-0.1.0.dist-info/METADATA
anum-0.1.0.dist-info/WHEEL
anum-0.1.0.dist-info/licenses/LICENSE
anum-0.1.0.dist-info/RECORD
