Metadata-Version: 2.1
Name: anum
Version: 0.1.0
Summary: Conjunto de ferramentas para implementação de métodos elementares de análise numérica
Project-URL: Homepage, https://github.com/GHM-ML/anum
Project-URL: Bug Tracker, https://github.com/GHM-ML/anum/issues
Author-email: Gabriel Martins <gabe.hm.ml@gmail.com>
License-File: LICENSE
Classifier: License :: OSI Approved :: MIT License
Classifier: Operating System :: OS Independent
Classifier: Programming Language :: Python :: 3
Requires-Python: >=3.9
